django_mailcss/__init__.py
django_mailcss/conf.py
django_mailcss/css_loaders.py
django_mailcss/engines.py
django_mailcss/models.py
django_mailcss/templatetags/__init__.py
django_mailcss/templatetags/mailcss.py
django_mailcss/tests/__init__.py
django_mailcss/tests/constants.py
django_mailcss/tests/test_css_loaders.py
django_mailcss/tests/test_templatetags.py
django_mailcss-0.1.0.dist-info/DESCRIPTION.rst
django_mailcss-0.1.0.dist-info/METADATA
django_mailcss-0.1.0.dist-info/RECORD
django_mailcss-0.1.0.dist-info/WHEEL
django_mailcss-0.1.0.dist-info/metadata.json
django_mailcss-0.1.0.dist-info/top_level.txt
