Metadata-Version: 2.0
Name: django-mailcss
Version: 0.1.0
Summary: A Django app useful for inlining CSS (primarily for e-mails)
Home-page: https://github.com/wejhink/django-mailcss
Author: Ch Ray
Author-email: ray@jhink.com
License: BSD
Download-URL: https://github.com/wejhink/django-mailcss/releases
Keywords: html,css,inline,style,email
Platform: UNKNOWN
Classifier: Environment :: Other Environment
Classifier: Environment :: Web Environment
Classifier: Intended Audience :: Developers
Classifier: License :: OSI Approved :: BSD License
Classifier: Operating System :: OS Independent
Classifier: Programming Language :: Python
Classifier: Topic :: Communications :: Email
Classifier: Topic :: Text Processing :: Markup :: HTML
Requires-Dist: mock
Requires-Dist: pynliner
